nzshm_model/__init__.py
nzshm_model/branch_registry.py
nzshm_model/logic_tree/__init__.py
nzshm_model/logic_tree/branch.py
nzshm_model/logic_tree/correlation.py
nzshm_model/logic_tree/gmcm_logic_tree/__init__.py
nzshm_model/logic_tree/gmcm_logic_tree/logic_tree.py
nzshm_model/logic_tree/helpers.py
nzshm_model/logic_tree/logic_tree_base.py
nzshm_model/logic_tree/source_logic_tree/__init__.py
nzshm_model/logic_tree/source_logic_tree/branch_attribute.py
nzshm_model/logic_tree/source_logic_tree/fault_system_branch_set.py
nzshm_model/logic_tree/source_logic_tree/logic_tree.py
nzshm_model/logic_tree/source_logic_tree/toshi_api.py
nzshm_model/logic_tree/source_logic_tree/version1/__init__.py
nzshm_model/logic_tree/source_logic_tree/version1/logic_tree.py
nzshm_model/logic_tree/source_logic_tree/version1/slt_config.py
nzshm_model/model.py
nzshm_model/model_version.py
nzshm_model/model_versions/__init__.py
nzshm_model/model_versions/nshm_v1_0_0.py
nzshm_model/model_versions/nshm_v1_0_4.py
nzshm_model/psha_adapter/__init__.py
nzshm_model/psha_adapter/hazard_config.py
nzshm_model/psha_adapter/hazard_config_factory.py
nzshm_model/psha_adapter/openquake/__init__.py
nzshm_model/psha_adapter/openquake/hazard_config.py
nzshm_model/psha_adapter/openquake/hazard_config_compat.py
nzshm_model/psha_adapter/openquake/logic_tree.py
nzshm_model/psha_adapter/openquake/simple_nrml.py
nzshm_model/psha_adapter/openquake/toshi.py
nzshm_model/psha_adapter/openquake/uncertainty_models.py
nzshm_model/psha_adapter/psha_adapter_interface.py
nzshm_model/resources/GMM_JSON/gmcm_nshm_v1.0.0.json
nzshm_model/resources/GMM_JSON/gmcm_nshm_v1.0.4.json
nzshm_model/resources/GMM_LTs/NZ_NSHM_GMM_LT_final_EE.xml
nzshm_model/resources/GMM_LTs/NZ_NSHM_GMM_LT_final_EE_new_names.xml
nzshm_model/resources/HAZARD_CONFIG_JSON/oq_config_nshm_v1.0.0.json
nzshm_model/resources/HAZARD_CONFIG_JSON/oq_config_nshm_v1.0.4.json
nzshm_model/resources/SRM_JSON/nshm_v1.0.0.json
nzshm_model/resources/SRM_JSON/nshm_v1.0.0_v2.json
nzshm_model-0.14.1.dist-info/METADATA
nzshm_model-0.14.1.dist-info/WHEEL
nzshm_model-0.14.1.dist-info/entry_points.txt
nzshm_model-0.14.1.dist-info/RECORD
