Metadata-Version: 2.4
Name: nzshm-model
Version: 0.14.1
Summary: The logic tree definitions, final configurations, and versioning of the New Zealand | Aotearoa National Seismic Hazard Model
License-Expression: AGPL-3.0-or-later
Author: Chris B Chamberlain
Author-email: chrisbc@artisan.co.nz
Requires-Python: >=3.10,<4.0
Classifier: Programming Language :: Python :: 3
Classifier: Programming Language :: Python :: 3.10
Classifier: Programming Language :: Python :: 3.11
Classifier: Programming Language :: Python :: 3.12
Classifier: Programming Language :: Python :: 3.13
Classifier: Programming Language :: Python :: 3.14
Provides-Extra: scripts
Provides-Extra: toshi
Requires-Dist: boto3 ; extra == "toshi"
Requires-Dist: click ; extra == "scripts"
Requires-Dist: dacite (>=1.6.0)
Requires-Dist: lxml (>=6.0)
Requires-Dist: nshm-toshi-client ; extra == "toshi"
Requires-Dist: nzshm-common (>=0.9.0)
